jay_mcp/__init__.py
jay_mcp/cli.py
jay_mcp/main.py
jay_mcp/py.typed
jay_mcp/resources.py
jay_mcp/server.py
jay_mcp/tools.py
jay_mcp/config/github_config.py
jay_mcp/models/github_repo_info.py
jay_mcp/services/github_api_service.py
jay_mcp/utils/response.py
jay_mcp-0.2.1.dist-info/licenses/LICENSE
jay_mcp-0.2.1.dist-info/METADATA
jay_mcp-0.2.1.dist-info/WHEEL
jay_mcp-0.2.1.dist-info/entry_points.txt
jay_mcp-0.2.1.dist-info/top_level.txt
jay_mcp-0.2.1.dist-info/RECORD
