Metadata-Version: 2.4
Name: jay-mcp
Version: 0.2.1
Summary: MCP server for batch GitHub repository information retrieval with parallel processing
Author-email: Jay MCP Team <contact@example.com>
Maintainer-email: Jay MCP Team <contact@example.com>
License-Expression: MIT
Project-URL: Homepage, https://github.com/your-username/jay-mcp
Project-URL: Repository, https://github.com/your-username/jay-mcp
Project-URL: Documentation, https://github.com/your-username/jay-mcp#readme
Project-URL: Bug Tracker, https://github.com/your-username/jay-mcp/issues
Keywords: mcp,model-context-protocol,github,repository,batch,api,ai,tools
Classifier: Development Status :: 3 - Alpha
Classifier: Intended Audience :: Developers
Classifier: Operating System :: OS Independent
Classifier: Programming Language :: Python :: 3
Classifier: Programming Language :: Python :: 3.8
Classifier: Programming Language :: Python :: 3.9
Classifier: Programming Language :: Python :: 3.10
Classifier: Programming Language :: Python :: 3.11
Classifier: Programming Language :: Python :: 3.12
Classifier: Topic :: Software Development :: Libraries :: Python Modules
Classifier: Topic :: Scientific/Engineering :: Artificial Intelligence
Requires-Python: >=3.8
License-File: LICENSE
Requires-Dist: mcp>=0.1.0
Requires-Dist: aiohttp>=3.8.0
Requires-Dist: fastapi>=0.100.0
Requires-Dist: pydantic>=2.0.0
Provides-Extra: dev
Requires-Dist: pytest>=7.0; extra == "dev"
Requires-Dist: pytest-cov>=4.0; extra == "dev"
Requires-Dist: black>=23.0; extra == "dev"
Requires-Dist: isort>=5.0; extra == "dev"
Requires-Dist: flake8>=6.0; extra == "dev"
Requires-Dist: mypy>=1.0; extra == "dev"
Dynamic: license-file
